{
    "display": {
        "title": {
            "text": "Manta!",
            "bold": false,
            "color": "red"
        },
        "description": {
            "text": "Скрафтите Manta Aio",
            "italic": true
        },
        "icon": {
            "item": "minecraft:carrot_on_a_stick",
            "nbt": "{CustomModelData:2}"
        },
        "frame": "task",
        "show_toast": true,
        "announce_to_chat": false,
        "hidden": false
        
    },
    "criteria": {
        "Ok": {
            "trigger": "minecraft:impossible"
        }
    },
    "parent": "nbt:start"
}