{
	"credit": "Made with Blockbench",
	"textures": {
		"0": "block/gray_shulker_box",
		"1": "block/lime_concrete",
		"particle": "block/gray_shulker_box"
	},
	"elements": [
		{
			"name": "hexadecagon",
			"from": [7.60218, 0, 6],
			"to": [8.39782, 13, 10],
			"rotation": {"angle": -45, "axis": "y", "origin": [8, 5, 8]},
			"faces": {
				"north": {"uv": [0, 0, 5, 5], "texture": "#0"},
				"east": {"uv": [0, 0, 5, 5], "texture": "#0"},
				"south": {"uv": [0, 0, 5, 5], "texture": "#0"},
				"west": {"uv": [0, 0, 5, 5], "texture": "#0"},
				"up": {"uv": [0, 0, 5, 5], "texture": "#0"},
				"down": {"uv": [0, 0, 5, 5], "texture": "#0"}
			}
		},
		{
			"name": "hexadecagon",
			"from": [7.60218, 0, 6],
			"to": [8.39782, 13, 10],
			"rotation": {"angle": -22.5, "axis": "y", "origin": [8, 5, 8]},
			"faces": {
				"north": {"uv": [0, 0, 5, 5], "texture": "#0"},
				"east": {"uv": [0, 0, 5, 5], "texture": "#0"},
				"south": {"uv": [0, 0, 5, 5], "texture": "#0"},
				"west": {"uv": [0, 0, 5, 5], "texture": "#0"},
				"up": {"uv": [0, 0, 5, 5], "texture": "#0"},
				"down": {"uv": [0, 0, 5, 5], "texture": "#0"}
			}
		},
		{
			"name": "hexadecagon",
			"from": [7.60218, 0, 6],
			"to": [8.39782, 13, 10],
			"rotation": {"angle": 0, "axis": "y", "origin": [8, 5, 8]},
			"faces": {
				"north": {"uv": [0, 0, 5, 5], "texture": "#0"},
				"east": {"uv": [0, 0, 5, 5], "texture": "#0"},
				"south": {"uv": [0, 0, 5, 5], "texture": "#0"},
				"west": {"uv": [0, 0, 5, 5], "texture": "#0"},
				"up": {"uv": [0, 0, 5, 5], "texture": "#0"},
				"down": {"uv": [0, 0, 5, 5], "texture": "#0"}
			}
		},
		{
			"name": "hexadecagon",
			"from": [7.60218, 0, 6],
			"to": [8.39782, 13, 10],
			"rotation": {"angle": 22.5, "axis": "y", "origin": [8, 5, 8]},
			"faces": {
				"north": {"uv": [0, 0, 5, 5], "texture": "#0"},
				"east": {"uv": [0, 0, 5, 5], "texture": "#0"},
				"south": {"uv": [0, 0, 5, 5], "texture": "#0"},
				"west": {"uv": [0, 0, 5, 5], "texture": "#0"},
				"up": {"uv": [0, 0, 5, 5], "texture": "#0"},
				"down": {"uv": [0, 0, 5, 5], "texture": "#0"}
			}
		},
		{
			"name": "hexadecagon",
			"from": [7.60218, 0, 6],
			"to": [8.39782, 13, 10],
			"rotation": {"angle": 45, "axis": "y", "origin": [8, 5, 8]},
			"faces": {
				"north": {"uv": [0, 0, 5, 5], "texture": "#0"},
				"east": {"uv": [0, 0, 5, 5], "texture": "#0"},
				"south": {"uv": [0, 0, 5, 5], "texture": "#0"},
				"west": {"uv": [0, 0, 5, 5], "texture": "#0"},
				"up": {"uv": [0, 0, 5, 5], "texture": "#0"},
				"down": {"uv": [0, 0, 5, 5], "texture": "#0"}
			}
		},
		{
			"name": "hexadecagon",
			"from": [6, 0, 7.60218],
			"to": [10, 13, 8.39782],
			"rotation": {"angle": -22.5, "axis": "y", "origin": [8, 5, 8]},
			"faces": {
				"north": {"uv": [0, 0, 5, 5], "texture": "#0"},
				"east": {"uv": [0, 0, 5, 5], "texture": "#0"},
				"south": {"uv": [0, 0, 5, 5], "texture": "#0"},
				"west": {"uv": [0, 0, 5, 5], "texture": "#0"},
				"up": {"uv": [0, 0, 5, 5], "texture": "#0"},
				"down": {"uv": [0, 0, 5, 5], "texture": "#0"}
			}
		},
		{
			"name": "hexadecagon",
			"from": [6, 0, 7.60218],
			"to": [10, 13, 8.39782],
			"rotation": {"angle": 0, "axis": "y", "origin": [8, 5, 8]},
			"faces": {
				"north": {"uv": [0, 0, 5, 5], "texture": "#0"},
				"east": {"uv": [0, 0, 5, 5], "texture": "#0"},
				"south": {"uv": [0, 0, 5, 5], "texture": "#0"},
				"west": {"uv": [0, 0, 5, 5], "texture": "#0"},
				"up": {"uv": [0, 0, 5, 5], "texture": "#0"},
				"down": {"uv": [0, 0, 5, 5], "texture": "#0"}
			}
		},
		{
			"name": "hexadecagon",
			"from": [6, 0, 7.60218],
			"to": [10, 13, 8.39782],
			"rotation": {"angle": 22.5, "axis": "y", "origin": [8, 5, 8]},
			"faces": {
				"north": {"uv": [0, 0, 5, 5], "texture": "#0"},
				"east": {"uv": [0, 0, 5, 5], "texture": "#0"},
				"south": {"uv": [0, 0, 5, 5], "texture": "#0"},
				"west": {"uv": [0, 0, 5, 5], "texture": "#0"},
				"up": {"uv": [0, 0, 5, 5], "texture": "#0"},
				"down": {"uv": [0, 0, 5, 5], "texture": "#0"}
			}
		},
		{
			"name": "hexadecagon",
			"from": [7.59223, 0, 5.95],
			"to": [8.40777, 13, 6.05],
			"rotation": {"angle": -45, "axis": "y", "origin": [8, 5, 8]},
			"faces": {
				"north": {"uv": [0, 0, 1, 1], "texture": "#1"},
				"east": {"uv": [0, 0, 1, 1], "texture": "#1"},
				"south": {"uv": [0, 0, 1, 1], "texture": "#1"},
				"west": {"uv": [0, 0, 1, 1], "texture": "#1"},
				"up": {"uv": [0, 0, 1, 1], "texture": "#1"},
				"down": {"uv": [0, 0, 1, 1], "texture": "#1"}
			}
		},
		{
			"name": "hexadecagon",
			"from": [7.59223, 0, 5.95],
			"to": [8.40777, 13, 6.05],
			"rotation": {"angle": -22.5, "axis": "y", "origin": [8, 5, 8]},
			"faces": {
				"north": {"uv": [0, 0, 1, 1], "texture": "#1"},
				"east": {"uv": [0, 0, 1, 1], "texture": "#1"},
				"south": {"uv": [0, 0, 1, 1], "texture": "#1"},
				"west": {"uv": [0, 0, 1, 1], "texture": "#1"},
				"up": {"uv": [0, 0, 1, 1], "texture": "#1"},
				"down": {"uv": [0, 0, 1, 1], "texture": "#1"}
			}
		},
		{
			"name": "hexadecagon",
			"from": [7.59223, 0, 5.95],
			"to": [8.40777, 13, 6.05],
			"rotation": {"angle": 0, "axis": "y", "origin": [8, 5, 8]},
			"faces": {
				"north": {"uv": [0, 0, 1, 1], "texture": "#1"},
				"east": {"uv": [0, 0, 1, 1], "texture": "#1"},
				"south": {"uv": [0, 0, 1, 1], "texture": "#1"},
				"west": {"uv": [0, 0, 1, 1], "texture": "#1"},
				"up": {"uv": [0, 0, 1, 1], "texture": "#1"},
				"down": {"uv": [0, 0, 1, 1], "texture": "#1"}
			}
		},
		{
			"name": "hexadecagon",
			"from": [7.59223, 0, 5.95],
			"to": [8.40777, 13, 6.05],
			"rotation": {"angle": 22.5, "axis": "y", "origin": [8, 5, 8]},
			"faces": {
				"north": {"uv": [0, 0, 1, 1], "texture": "#1"},
				"east": {"uv": [0, 0, 1, 1], "texture": "#1"},
				"south": {"uv": [0, 0, 1, 1], "texture": "#1"},
				"west": {"uv": [0, 0, 1, 1], "texture": "#1"},
				"up": {"uv": [0, 0, 1, 1], "texture": "#1"},
				"down": {"uv": [0, 0, 1, 1], "texture": "#1"}
			}
		},
		{
			"name": "hexadecagon",
			"from": [7.59223, 0, 5.95],
			"to": [8.40777, 13, 6.05],
			"rotation": {"angle": 45, "axis": "y", "origin": [8, 5, 8]},
			"faces": {
				"north": {"uv": [0, 0, 1, 1], "texture": "#1"},
				"east": {"uv": [0, 0, 1, 1], "texture": "#1"},
				"south": {"uv": [0, 0, 1, 1], "texture": "#1"},
				"west": {"uv": [0, 0, 1, 1], "texture": "#1"},
				"up": {"uv": [0, 0, 1, 1], "texture": "#1"},
				"down": {"uv": [0, 0, 1, 1], "texture": "#1"}
			}
		},
		{
			"name": "hexadecagon",
			"from": [7.59223, 0, 9.95],
			"to": [8.40777, 13, 10.05],
			"rotation": {"angle": -45, "axis": "y", "origin": [8, 5, 8]},
			"faces": {
				"north": {"uv": [0, 0, 1, 1], "texture": "#1"},
				"east": {"uv": [0, 0, 1, 1], "texture": "#1"},
				"south": {"uv": [0, 0, 1, 1], "texture": "#1"},
				"west": {"uv": [0, 0, 1, 1], "texture": "#1"},
				"up": {"uv": [0, 0, 1, 1], "texture": "#1"},
				"down": {"uv": [0, 0, 1, 1], "texture": "#1"}
			}
		},
		{
			"name": "hexadecagon",
			"from": [7.59223, 0, 9.95],
			"to": [8.40777, 13, 10.05],
			"rotation": {"angle": -22.5, "axis": "y", "origin": [8, 5, 8]},
			"faces": {
				"north": {"uv": [0, 0, 1, 1], "texture": "#1"},
				"east": {"uv": [0, 0, 1, 1], "texture": "#1"},
				"south": {"uv": [0, 0, 1, 1], "texture": "#1"},
				"west": {"uv": [0, 0, 1, 1], "texture": "#1"},
				"up": {"uv": [0, 0, 1, 1], "texture": "#1"},
				"down": {"uv": [0, 0, 1, 1], "texture": "#1"}
			}
		},
		{
			"name": "hexadecagon",
			"from": [7.59223, 0, 9.95],
			"to": [8.40777, 13, 10.05],
			"rotation": {"angle": 0, "axis": "y", "origin": [8, 5, 8]},
			"faces": {
				"north": {"uv": [0, 0, 1, 1], "texture": "#1"},
				"east": {"uv": [0, 0, 1, 1], "texture": "#1"},
				"south": {"uv": [0, 0, 1, 1], "texture": "#1"},
				"west": {"uv": [0, 0, 1, 1], "texture": "#1"},
				"up": {"uv": [0, 0, 1, 1], "texture": "#1"},
				"down": {"uv": [0, 0, 1, 1], "texture": "#1"}
			}
		},
		{
			"name": "hexadecagon",
			"from": [7.59223, 0, 9.95],
			"to": [8.40777, 13, 10.05],
			"rotation": {"angle": 22.5, "axis": "y", "origin": [8, 5, 8]},
			"faces": {
				"north": {"uv": [0, 0, 1, 1], "texture": "#1"},
				"east": {"uv": [0, 0, 1, 1], "texture": "#1"},
				"south": {"uv": [0, 0, 1, 1], "texture": "#1"},
				"west": {"uv": [0, 0, 1, 1], "texture": "#1"},
				"up": {"uv": [0, 0, 1, 1], "texture": "#1"},
				"down": {"uv": [0, 0, 1, 1], "texture": "#1"}
			}
		},
		{
			"name": "hexadecagon",
			"from": [7.59223, 0, 9.95],
			"to": [8.40777, 13, 10.05],
			"rotation": {"angle": 45, "axis": "y", "origin": [8, 5, 8]},
			"faces": {
				"north": {"uv": [0, 0, 1, 1], "texture": "#1"},
				"east": {"uv": [0, 0, 1, 1], "texture": "#1"},
				"south": {"uv": [0, 0, 1, 1], "texture": "#1"},
				"west": {"uv": [0, 0, 1, 1], "texture": "#1"},
				"up": {"uv": [0, 0, 1, 1], "texture": "#1"},
				"down": {"uv": [0, 0, 1, 1], "texture": "#1"}
			}
		},
		{
			"name": "hexadecagon",
			"from": [5.95, 0, 7.59223],
			"to": [6.05, 13, 8.40777],
			"rotation": {"angle": -22.5, "axis": "y", "origin": [8, 5, 8]},
			"faces": {
				"north": {"uv": [0, 0, 1, 1], "texture": "#1"},
				"east": {"uv": [0, 0, 1, 1], "texture": "#1"},
				"south": {"uv": [0, 0, 1, 1], "texture": "#1"},
				"west": {"uv": [0, 0, 1, 1], "texture": "#1"},
				"up": {"uv": [0, 0, 1, 1], "texture": "#1"},
				"down": {"uv": [0, 0, 1, 1], "texture": "#1"}
			}
		},
		{
			"name": "hexadecagon",
			"from": [5.95, 0, 7.59223],
			"to": [6.05, 13, 8.40777],
			"rotation": {"angle": 0, "axis": "y", "origin": [8, 5, 8]},
			"faces": {
				"north": {"uv": [0, 0, 1, 1], "texture": "#1"},
				"east": {"uv": [0, 0, 1, 1], "texture": "#1"},
				"south": {"uv": [0, 0, 1, 1], "texture": "#1"},
				"west": {"uv": [0, 0, 1, 1], "texture": "#1"},
				"up": {"uv": [0, 0, 1, 1], "texture": "#1"},
				"down": {"uv": [0, 0, 1, 1], "texture": "#1"}
			}
		},
		{
			"name": "hexadecagon",
			"from": [5.95, 0, 7.59223],
			"to": [6.05, 13, 8.40777],
			"rotation": {"angle": 22.5, "axis": "y", "origin": [8, 5, 8]},
			"faces": {
				"north": {"uv": [0, 0, 1, 1], "texture": "#1"},
				"east": {"uv": [0, 0, 1, 1], "texture": "#1"},
				"south": {"uv": [0, 0, 1, 1], "texture": "#1"},
				"west": {"uv": [0, 0, 1, 1], "texture": "#1"},
				"up": {"uv": [0, 0, 1, 1], "texture": "#1"},
				"down": {"uv": [0, 0, 1, 1], "texture": "#1"}
			}
		},
		{
			"name": "hexadecagon",
			"from": [9.95, 0, 7.59223],
			"to": [10.05, 13, 8.40777],
			"rotation": {"angle": -22.5, "axis": "y", "origin": [8, 5, 8]},
			"faces": {
				"north": {"uv": [0, 0, 1, 1], "texture": "#1"},
				"east": {"uv": [0, 0, 1, 1], "texture": "#1"},
				"south": {"uv": [0, 0, 1, 1], "texture": "#1"},
				"west": {"uv": [0, 0, 1, 1], "texture": "#1"},
				"up": {"uv": [0, 0, 1, 1], "texture": "#1"},
				"down": {"uv": [0, 0, 1, 1], "texture": "#1"}
			}
		},
		{
			"name": "hexadecagon",
			"from": [9.95, 0, 7.59223],
			"to": [10.05, 13, 8.40777],
			"rotation": {"angle": 0, "axis": "y", "origin": [8, 5, 8]},
			"faces": {
				"north": {"uv": [0, 0, 1, 1], "texture": "#1"},
				"east": {"uv": [0, 0, 1, 1], "texture": "#1"},
				"south": {"uv": [0, 0, 1, 1], "texture": "#1"},
				"west": {"uv": [0, 0, 1, 1], "texture": "#1"},
				"up": {"uv": [0, 0, 1, 1], "texture": "#1"},
				"down": {"uv": [0, 0, 1, 1], "texture": "#1"}
			}
		},
		{
			"name": "hexadecagon",
			"from": [9.95, 0, 7.59223],
			"to": [10.05, 13, 8.40777],
			"rotation": {"angle": 22.5, "axis": "y", "origin": [8, 5, 8]},
			"faces": {
				"north": {"uv": [0, 0, 1, 1], "texture": "#1"},
				"east": {"uv": [0, 0, 1, 1], "texture": "#1"},
				"south": {"uv": [0, 0, 1, 1], "texture": "#1"},
				"west": {"uv": [0, 0, 1, 1], "texture": "#1"},
				"up": {"uv": [0, 0, 1, 1], "texture": "#1"},
				"down": {"uv": [0, 0, 1, 1], "texture": "#1"}
			}
		}
	],
	"display": {
		"thirdperson_righthand": {
			"scale": [0.2, 0.2, 0.2]
		},
		"thirdperson_lefthand": {
			"scale": [0.2, 0.2, 0.2]
		},
		"firstperson_righthand": {
			"scale": [0.2, 0.2, 0.2]
		},
		"firstperson_lefthand": {
			"scale": [0.2, 0.2, 0.2]
		},
		"ground": {
			"rotation": [-18.94, 1.04, -6.15],
			"scale": [0.2, 0.2, 0.2]
		},
		"gui": {
			"rotation": [38.08, 43.53, -24.27],
			"translation": [0, 0.5, 0]
		},
		"head": {
			"scale": [0.2, 0.2, 0.2]
		},
		"fixed": {
			"rotation": [12.96, -28.13, 25.98],
			"scale": [0.2, 0.2, 0.2]
		}
	},
	"groups": [
		{
			"name": "hexadecagon",
			"origin": [8, 8, 8],
			"color": 0,
			"children": [0, 1, 2, 3, 4, 5, 6, 7]
		},
		{
			"name": "hexadecagon",
			"origin": [8, 8, 8],
			"color": 0,
			"children": [8, 9, 10, 11, 12, 13, 14, 15, 16, 17, 18, 19, 20, 21, 22, 23]
		}
	]
}